LICENSE
MANIFEST.in
README.rst
setup.cfg
setup.py
src/sentry_opsgenie/__init__.py
src/sentry_opsgenie/plugin.py
src/sentry_opsgenie.egg-info/PKG-INFO
src/sentry_opsgenie.egg-info/SOURCES.txt
src/sentry_opsgenie.egg-info/dependency_links.txt
src/sentry_opsgenie.egg-info/entry_points.txt
src/sentry_opsgenie.egg-info/not-zip-safe
src/sentry_opsgenie.egg-info/requires.txt
src/sentry_opsgenie.egg-info/top_level.txt