Metadata-Version: 1.1
Name: sentry-opsgenie
Version: 0.1.0
Summary: A Sentry extension which posts notifications to OpsGenie (https://www.opsgenie.com/).
Home-page: https://github.com/getsentry/sentry-opsgenie
Author: David Cramer
Author-email: dcramer@gmail.com
License: Apache 2.0
Platform: UNKNOWN
Classifier: Framework :: Django
Classifier: Intended Audience :: Developers
Classifier: Intended Audience :: System Administrators
Classifier: Operating System :: OS Independent
Classifier: Topic :: Software Development
